{
	"frontend": [
		{
			"title": "Testimonials Grid Section",
			"url": "https://gabcchaves.github.io/Testimonials-grid-section/",
			"img": "https://raw.githubusercontent.com/gabcchaves/Testimonials-grid-section/main/screenshot.png",
			"description": "Testimonials comment."
		},
		{
			"title": "Profile Card Component",
			"url": "https://gabcchaves.github.io/Profile-Card-Component/",
			"img": "https://raw.githubusercontent.com/gabcchaves/Profile-Card-Component/main/screenshot.png",
			"description": "Simple profile card."
		},
		{
			"title": "Login Page",
			"url": "https://gabcchaves.github.io/login-page/",
			"img": "https://raw.githubusercontent.com/gabcchaves/login-page/main/screenshot.png",
			"description": "Simple login page using Bootstrap."
		},
		{
			"title": "Registration Page",
			"url": "https://gabcchaves.github.io/registration-page/",
			"img": "https://raw.githubusercontent.com/gabcchaves/registration-page/main/screenshot.png",
			"description": "Simple registration page using Bootstrap."
		},
		{
			"title": "NFT Preview Card Component",
			"url": "https://gabcchaves.github.io/nft-preview-card-component/",
			"img": "https://raw.githubusercontent.com/gabcchaves/nft-preview-card-component/main/images/preview.png",
			"description": "Preview card."
		},
		{
			"title": "QR Code Component",
			"url": "https://gabcchaves.github.io/qr-code-component/",
			"img": "https://raw.githubusercontent.com/gabcchaves/qr-code-component/8ba7a03ee494d6847af7b069017e13816f57160d/images/preview.png",
			"description": "Simple QR code card."
		},
		{
			"title": "Interactive Rating Component",
			"url": "https://gabcchaves.github.io/interactive-rating-component-main",
			"img": "https://raw.githubusercontent.com/gabcchaves/interactive-rating-component-main/main/screenshot.png",
			"description": "Interactive rating component. Front end project from FrontendMentor."
		},
		{
			"title": "3 Column Preview Card Component",
			"url": "https://gabcchaves.github.io/3-column-preview-card-component-main",
			"img": "https://raw.githubusercontent.com/gabcchaves/3-column-preview-card-component-main/main/screenshot.png",
			"description": "3 column preview cards component."
		},
		{
			"title": "Stats Preview Card Component",
			"url": "https://gabcchaves.github.io/stats-preview-card-component-main",
			"img": "https://raw.githubusercontent.com/gabcchaves/stats-preview-card-component-main/master/screenshot.png",
			"description": "Stats preview card component."
		},
		{
			"title": "Product Preview Card Component",
			"url": "https://gabcchaves.github.io/product-preview-card-component-main",
			"img": "https://raw.githubusercontent.com/gabcchaves/product-preview-card-component-main/master/screenshot.png",
			"description": "Product preview card component."
		},
		{
			"title": "Order Summary Component",
			"url": "https://gabcchaves.github.io/order-summary-component-main",
			"img": "https://raw.githubusercontent.com/gabcchaves/order-summary-component-main/main/screenshot.png",
			"description": "Order summary component."
		},
		{
			"title": "Login form",
			"url": "https://gabcchaves.github.io/login-form",
			"img": "https://raw.githubusercontent.com/gabcchaves/login-form/master/screenshot.png",
			"description": "Login form."
		},
		{
			"title": "FAQ Accordion Card",
			"url": "https://gabcchaves.github.io/faq-accordion-card",
			"img": "https://raw.githubusercontent.com/gabcchaves/faq-accordion-card/main/screenshot.png",
			"description": "FAQ accordion card."
		},
		{
			"title": "Four Card Feature Section",
			"url": "https://gabcchaves.github.io/four-card-feature-section",
			"img": "https://raw.githubusercontent.com/gabcchaves/four-card-feature-section/main/screenshot.png",
			"description": "Four card feature section."
		},
		{
			"title": "Social Proof Section",
			"url": "https://gabcchaves.github.io/social-proof-section",
			"img": "https://raw.githubusercontent.com/gabcchaves/social-proof-section/main/screenshot.png",
			"description": "Social proof section."
		},
		{
			"title": "Article Preview Component",
			"url": "https://gabcchaves.github.io/article-preview-component",
			"img": "https://raw.githubusercontent.com/gabcchaves/article-preview-component/main/screenshot.png",
			"description": "Article preview component."
		},
		{
			"title": "Base Apparel Coming Soon",
			"url": "https://gabcchaves.github.io/base-apparel-coming-soon",
			"img": "https://raw.githubusercontent.com/gabcchaves/base-apparel-coming-soon/main/screenshot.png",
			"description": "Base apparel coming soon."
		},
		{
			"title": "Huddle Landing Page With Single Introductory Section",
			"url": "https://gabcchaves.github.io/huddle-landing-page-with-single-introductory-section",
			"img": "https://raw.githubusercontent.com/gabcchaves/huddle-landing-page-with-single-introductory-section/main/screenshot.png",
			"description": "Huddle landing page with single introductory section."
		},
		{
			"title": "Ping Coming Soon Page",
			"url": "https://gabcchaves.github.io/ping-coming-soon-page",
			"img": "https://raw.githubusercontent.com/gabcchaves/ping-coming-soon-page/main/screenshot.png",
			"description": "Ping coming soon page."
		},
		{
			"title": "Single Price Grid Component",
			"url": "https://gabcchaves.github.io/single-price-grid-component",
			"img": "https://raw.githubusercontent.com/gabcchaves/single-price-grid-component/main/screenshot.png",
			"description": "Single price grid component."
		},
		{
			"title": "Intro Component With Signup Form",
			"url": "https://gabcchaves.github.io/intro-component-with-signup-form",
			"img": "https://raw.githubusercontent.com/gabcchaves/intro-component-with-signup-form/main/screenshot.png",
			"description": "Intro component with signup form."
		},
		{
			"title": "Interactive Card Details Form",
			"url": "https://gabcchaves.github.io/interactive-card-details-form",
			"img": "https://raw.githubusercontent.com/gabcchaves/interactive-card-details-form/main/screenshot.png",
			"description": "Interactive card details form."
		},
		{
			"title": "Expenses Chart Component",
			"url": "https://gabcchaves.github.io/expenses-chart-component",
			"img": "https://raw.githubusercontent.com/gabcchaves/expenses-chart-component/main/screenshot.png",
			"description": "Expenses chart component."
		},
		{
			"title": "Intro Section With Dropdown Navigation",
			"url": "https://gabcchaves.github.io/intro-section-with-dropdown-navigation",
			"img": "https://raw.githubusercontent.com/gabcchaves/intro-section-with-dropdown-navigation/main/screenshot.png",
			"description": "Intro section with dropdown navigation."
		},
		{
			"title": "Advice generator app",
			"url": "https://gabcchaves.github.io/advice-generator-app",
			"img": "https://raw.githubusercontent.com/gabcchaves/advice-generator-app/main/screenshot.png",
			"description": "Advice generator app."
		},
		{
			"title": "Time Tracking Dashboard",
			"url": "https://gabcchaves.github.io/time-tracking-dashboard",
			"img": "https://raw.githubusercontent.com/gabcchaves/time-tracking-dashboard/main/screenshot.png",
			"description": "Time tracking dashboad."
		},
		{
			"title": "Tip Calculator App",
			"url": "https://gabcchaves.github.io/tip-calculator-app",
			"img": "https://raw.githubusercontent.com/gabcchaves/tip-calculator-app/main/screenshot.png",
			"description": "Tip calculator app."
		},
		{
			"title": "Sunnyside Agency Landing Page",
			"url": "https://gabcchaves.github.io/sunnyside-agency-landing-page",
			"img": "https://raw.githubusercontent.com/gabcchaves/sunnyside-agency-landing-page/main/screenshot.png",
			"description": "Sunnyside agency landing page."
		},
		{
			"title": "Blogr Landing Page",
			"url": "https://gabcchaves.github.io/blogr-landing-page",
			"img": "https://raw.githubusercontent.com/gabcchaves/blogr-landing-page/master/screenshot.png",
			"description": "Blogr landing page."
		}
	],
	"fullstack": [
		{
			"title": "Plantê",
			"url": "https://github.com/gabcchaves/plante",
			"img": "",
			"description": "Sistema de venda de plantas."
		},
		{
			"title": "User Manager",
			"url": "https://gabcchaves.github.io/user-manager",
			"img": "",
			"description": "User manager web system. Merely a practise of Rust and Yew framework."
		}
	]
}
